main.py
source_wikipedia_pageviews/__init__.py
source_wikipedia_pageviews/manifest.yaml
source_wikipedia_pageviews/run.py
source_wikipedia_pageviews/source.py
airbyte_source_wikipedia_pageviews-0.1.10.dist-info/METADATA
airbyte_source_wikipedia_pageviews-0.1.10.dist-info/WHEEL
airbyte_source_wikipedia_pageviews-0.1.10.dist-info/entry_points.txt
airbyte_source_wikipedia_pageviews-0.1.10.dist-info/RECORD
