Metadata-Version: 2.1
Name: airbyte-source-wikipedia-pageviews
Version: 0.1.10
Summary: Source implementation for wikipedia-pageviews.
Home-page: https://airbyte.com
License: MIT
Author: Airbyte
Author-email: contact@airbyte.io
Requires-Python: >=3.9,<3.12
Classifier: License :: OSI Approved :: MIT License
Classifier: Programming Language :: Python :: 3
Classifier: Programming Language :: Python :: 3.9
Classifier: Programming Language :: Python :: 3.10
Classifier: Programming Language :: Python :: 3.11
Requires-Dist: airbyte-cdk (>=2,<3)
Project-URL: Documentation, https://docs.airbyte.com/integrations/sources/wikipedia-pageviews
Project-URL: Repository, https://github.com/airbytehq/airbyte
